motion_photo_splitter/__init__.py
motion_photo_splitter/__main__.py
motion_photo_splitter-1.1.0.dist-info/LICENSE
motion_photo_splitter-1.1.0.dist-info/METADATA
motion_photo_splitter-1.1.0.dist-info/WHEEL
motion_photo_splitter-1.1.0.dist-info/dependency_links.txt
motion_photo_splitter-1.1.0.dist-info/entry_points.txt
motion_photo_splitter-1.1.0.dist-info/top_level.txt
motion_photo_splitter-1.1.0.dist-info/RECORD
