Metadata-Version: 2.1
Name: motion-photo-splitter
Version: 1.1.0
Summary: CLI for splitting motion photo files into separate picture and vide file.
Home-page: https://github.com/gr4viton/motion_photo_splitter
Author: gr4viton
Author-email: lordmutty@gmail.com
License: MIT
Download-URL: https://github.com/gr4viton/motion_photo_splitter/archive/1.0.0.tar.gz
Platform: UNKNOWN
Classifier: License :: OSI Approved :: MIT License
Classifier: Programming Language :: Python :: 3
Classifier: Programming Language :: Python :: 3.7
Requires-Python: >=3.5
Requires-Dist: click
